{"stats":{"minecraft:killed_by":{"minecraft:creeper":1,"minecraft:zombie":1},"minecraft:killed":{"minecraft:skeleton":1},"minecraft:dropped":{"minecraft:arrow":4,"minecraft:bone":2},"minecraft:custom":{"minecraft:time_since_rest":53683,"minecraft:crouch_one_cm":249,"minecraft:play_time":328135,"minecraft:sprint_one_cm":126805,"minecraft:deaths":2,"minecraft:damage_taken":1028,"minecraft:walk_one_cm":39391,"minecraft:sneak_time":154,"minecraft:walk_under_water_one_cm":1560,"minecraft:mob_kills":1,"minecraft:drop":6,"minecraft:jump":988,"minecraft:damage_dealt":301,"minecraft:leave_game":14,"minecraft:time_since_death":53650,"minecraft:total_world_time":328135,"minecraft:fly_one_cm":377263,"minecraft:fall_one_cm":4274},"minecraft:picked_up":{"minecraft:bone":2,"minecraft:arrow":4}},"DataVersion":3955}